eippred/Data/AAIndexNames.csv
eippred/Data/Grantham.csv
eippred/Data/PhysicoChemical.csv
eippred/Data/Schneider-Wrede.csv
eippred/Data/aa_attr_group.csv
eippred/Data/aaind.txt
eippred/Data/aaindex.csv
eippred/Data/aaindices.csv
eippred/Data/atom.csv
eippred/Data/bin_di.csv
eippred/Data/bonds.csv
eippred/Data/can_pat.csv
eippred/Data/data
eippred/Data/model2.pkl
eippred/Data/selected_features_mrmr1000_new.csv
eippred/Data/z_aaindex.csv
eippred/python_scripts/__init__.py
eippred/python_scripts/eippred.py
eippred-1.0.4.dist-info/METADATA
eippred-1.0.4.dist-info/WHEEL
eippred-1.0.4.dist-info/entry_points.txt
eippred-1.0.4.dist-info/top_level.txt
eippred-1.0.4.dist-info/RECORD
