Metadata-Version: 2.1
Name: eippred
Version: 1.0.4
Summary: EIPPred: A tool for predicting, and designing MIC of the  peptides
Home-page: https://github.com/raghavalab/eippred
Author: Nisha Bajiya
Author-email: nishab@iiitd.ac.in
Requires-Python: >=3.6
Requires-Dist: numpy
Requires-Dist: pandas
Requires-Dist: scikit-learn
Requires-Dist: argparse
Requires-Dist: tqdm
